{"assetGroup":{"chatChannelInfo":{"isChatChannelCreated":false,"channelUrl":null,"presentMembers":[]},"count":{"variations":1,"styles":1,"sizes":1,"creatives":1},"notifications":{"slack":{"threadId":null,"channelName":null}},"_id":"asset-group-69e5c38d6826b2da8c1d57a7","shortId":"DSNsZv85yqoI-1065","name":"Kids BAU flash - APR'26","image":"https://rocketium.com/img/workspace-placeholder-4.jpg","teamId":"623a177218b0b745935d7a49","variations":[{"_id":"2c3f0b4d-cbbf-4221-27dc-7ec93621a4b0","name":"Variant 1","styles":["2c3f0b4d-cbbf-4221-27dc-7ec93621a4b0"]}],"timestamp":"2026-04-20T06:12:25.934Z","draftLink":"https://rocketium.com/advertising/campaign/editor/DSNsZv85yqoI-1065/Kids-BAU-flash-APR-26","sizes":["00d503c2-198a-4040-2ad5-5bbc79f90f6a-412x724"],"groupIds":["6995779c3ff3f60a3c9e9102"],"parentGroupId":"6995779d3ff3f60a3c9e910f","isDeleted":false,"modifiedBy":"sampada.haralkar@nykaa.com","createdBy":"sampada.haralkar@nykaa.com","numberOfCreatives":1,"status":"draft","outputFormat":"image","tags":[],"templateId":"6995779d3ff3f60a3c9e910f","templateSizes":{"00d503c2-198a-4040-2ad5-5bbc79f90f6a-412x724":{"active":true,"name":"412x724","creativeUrl":"https://rocketium.com/images/export/6995779c3ff3f60a3c9e9102/412x724-00d503c2-198a-4040-2ad5-5bbc79f90f6a-412x724-1774244570561.png","width":412,"height":724,"thumbnail":"https://rocketium.com/images/thumbnail/6995779c3ff3f60a3c9e9102/412x724-00d503c2-198a-4040-2ad5-5bbc79f90f6a-412x724-1774244563196.webp","creativeHtmlUrl":null}},"amazonReviewers":[],"assetFolderId":null,"projectUID":"1065","withCanvas":true,"creativeFilenameData":[{"_id":"variantName","name":"Variant Name","separator":"_","isVisible":true},{"_id":"sizeKey","name":"Size","separator":"_","isVisible":true},{"_id":"sizeLabel","name":"Size Label","separator":"_","isVisible":false},{"_id":"projectName","name":"Project Name","separator":"_","isVisible":false}],"variables":[],"createdAt":"2026-04-20T06:11:25.597Z","updatedAt":"2026-04-20T06:12:25.956Z","__v":0,"customField":{"64363360efa6471844d79864":"eb530353-3513-4cf1-09d4-5849d3a29c2a-1","6863d9b9e049918c2dcf159c":"d8988d0a-e5b9-45eb-0079-ec5d824ed3e1-2","6863d9875e0edc7971f41b70":["62fdb10830765f30f93884a4"],"6863d97b2c7cf2bfea285551":["686b779c980a130bdcace43b"],"6396dc6c0f965717ae4283aa":"686b779c980a130bdcace43b","6863d9cae049918c2dcf15b2":"2026-04-20T13:30:45.652Z","6863d9d86ef91aadf0a2488f":"<p>use bright image</p>","6863d9e65a3cc2006aeb4e1b":"<p>Already given</p>","6863d9f06ef91aadf0a248a1":"<p>-</p>","6863d9fb2c7cf2bfea2855f3":"<p>-</p>","6863da075a3cc2006aeb4e61":"<p><a target=\"_blank\" rel=\"noopener noreferrer nofollow\" href=\"https://docs.google.com/spreadsheets/d/1FPDvGBuujJrEfkYBpPJpon5dgBICcNtCQrVgVEa1mws/edit?gid=1389471281#gid=1389471281\">https://docs.google.com/spreadsheets/d/1FPDvGBuujJrEfkYBpPJpon5dgBICcNtCQrVgVEa1mws/edit?gid=1389471281#gid=1389471281</a></p>","6870ce73db1176084247c592":"cf3e90f0-dee3-43c0-0526-d8ec8788226c-0","69afed847ca75d9649e72789":"68f830c6-3bf7-460f-0e78-64c13957f731-0","69afeda9c5a9dc733973298a":"<p>-</p>"},"sanitizedTextArea":{"6863d9d86ef91aadf0a2488f":"use bright image","6863d9e65a3cc2006aeb4e1b":"Already given","6863d9f06ef91aadf0a248a1":"-","6863d9fb2c7cf2bfea2855f3":"-","6863da075a3cc2006aeb4e61":"https://docs.google.com/spreadsheets/d/1FPDvGBuujJrEfkYBpPJpon5dgBICcNtCQrVgVEa1mws/edit?gid=1389471281#gid=1389471281","69afeda9c5a9dc733973298a":"-"}},"capsules":[{"_id":"69e5c3b52a533819d4043c85","capsuleId":"2c3f0b4d-cbbf-4221-27dc-7ec93621a4b0","version":1,"author":"Vanishree K - Rocketium","authorId":"6465b5ef12dd262b452cdd18","brandPalettes":[],"branding":true,"canvasData":{"metadata":{},"variant":{"id":"6995779c3ff3f60a3c9e9102","sizes":{"00d503c2-198a-4040-2ad5-5bbc79f90f6a-412x724":{"width":412,"height":724,"id":"00d503c2-198a-4040-2ad5-5bbc79f90f6a-412x724","displayName":"412x724","showGrid":false,"grid":{"size":50,"unit":"PIXEL","color":"#FF0000","subdivisions":1}}},"objects":{"7eec152d-151d-4d1f-8543-32324897ef13":{"id":"7eec152d-151d-4d1f-8543-32324897ef13","type":"rect","dataType":"CREATIVE_BOX","width":412,"height":724,"fill":"rgba(255,255,234,1)","groupPath":null,"zIndex":0,"overrides":{"00d503c2-198a-4040-2ad5-5bbc79f90f6a-412x724":{"zIndex":0}}},"732e83ef-e507-4768-2192-22ac85eb31cc":{"type":"image-container","id":"732e83ef-e507-4768-2192-22ac85eb31cc","displayText":"Full Image","dataType":"IMAGE","left":0,"top":0,"width":412,"height":590,"angle":0,"opacity":1,"filter":{"brightness":0,"saturation":0,"contrast":0,"invert":false,"blur":0},"shadow":null,"visible":true,"globalCompositeOperation":"source-over","selectable":true,"objectPosition":"center","flipX":false,"flipY":false,"imageOriginX":"center","imageOriginY":"center","border":{"stroke":"rgba(0, 0, 0, 1)","strokeWidth":0,"strokeDashArray":[0,0]},"fill":"transparent","padding":{"top":0,"right":0,"bottom":0,"left":0},"cornerRadius":{"tl":0,"tr":0,"bl":0,"br":0},"objectFit":"fill","imageScale":0.5008488964346349,"imageRotation":0,"imageLeft":0,"imageTop":0,"imageWidth":824,"imageHeight":1178,"src":"https://rocketium.com/images/v2/698c18884abb907eb9543a53/canvasPreview/af611575-8224-4e10-3990-eeba29d0f7b7.webp","exportSrc":"https://rocketium.com/images/v2/698c18884abb907eb9543a53/canvasExport/af611575-8224-4e10-3990-eeba29d0f7b7.png","originalSrc":"https://rocketium.com/images/v2/698c18884abb907eb9543a53/original/af611575-8224-4e10-3990-eeba29d0f7b7.png","layerRules":{},"groupPath":null,"reflection":null,"zIndex":1,"overrides":{"00d503c2-198a-4040-2ad5-5bbc79f90f6a-412x724":{"zIndex":1}}},"7e158756-f80a-41d1-8b3c-c04147e638b6":{"type":"image-container","id":"7e158756-f80a-41d1-8b3c-c04147e638b6","displayText":"Blur Bottom","dataType":"IMAGE","left":0,"top":466,"width":412,"height":124,"angle":0,"opacity":1,"filter":{"brightness":0,"saturation":0,"contrast":0,"invert":false,"blur":0.26},"shadow":null,"visible":true,"globalCompositeOperation":"source-over","selectable":true,"objectPosition":"bottom-center","flipX":false,"flipY":false,"imageOriginX":"center","imageOriginY":"bottom","border":{"stroke":"rgba(0, 0, 0, 1)","strokeWidth":0,"strokeDashArray":[0,0]},"fill":"transparent","padding":{"top":0,"right":0,"bottom":0,"left":0},"cornerRadius":{"tl":0,"tr":0,"bl":0,"br":0},"objectFit":"fill","imageScale":0.5,"imageRotation":0,"imageLeft":0,"imageTop":62,"imageWidth":824,"imageHeight":1178,"src":"https://rocketium.com/images/v2/698c18884abb907eb9543a53/canvasPreview/af611575-8224-4e10-3990-eeba29d0f7b7.webp","exportSrc":"https://rocketium.com/images/v2/698c18884abb907eb9543a53/canvasExport/af611575-8224-4e10-3990-eeba29d0f7b7.png","originalSrc":"https://rocketium.com/images/v2/698c18884abb907eb9543a53/original/af611575-8224-4e10-3990-eeba29d0f7b7.png","layerRules":{},"groupPath":null,"reflection":null,"zIndex":2,"overrides":{"00d503c2-198a-4040-2ad5-5bbc79f90f6a-412x724":{"zIndex":2}}},"10a1f4b7-ecee-4cd4-8618-c581e4fcdf15":{"id":"10a1f4b7-ecee-4cd4-8618-c581e4fcdf15","type":"rounded-rect","dataType":"SHAPE","displayText":"Solid Bottom","left":0,"top":466,"width":412,"height":124,"fill":"rgba(0, 0, 0, 1)","angle":0,"opacity":0.1,"shadow":null,"visible":true,"layerRules":{},"border":{"stroke":"rgba(0, 0, 0, 1)","strokeWidth":0,"strokeDashArray":[0,0]},"globalCompositeOperation":"source-over","selectable":true,"cornerRadius":{"tl":0,"tr":0,"br":0,"bl":0},"scale":1,"groupPath":null,"reflection":null,"zIndex":3,"overrides":{"00d503c2-198a-4040-2ad5-5bbc79f90f6a-412x724":{"zIndex":3}}},"05e1af0e-3d7d-4864-ad07-259344a2397f":{"id":"05e1af0e-3d7d-4864-ad07-259344a2397f","type":"rounded-rect","dataType":"SHAPE","displayText":"Solid Bottom Copy 2","left":0,"top":339,"width":412,"height":251,"fill":{"type":"linear","coords":{"x1":0.5,"y1":0,"x2":0.5,"y2":1},"colorStops":[{"color":"rgba(0, 0, 0, 1)","offset":1},{"color":"rgba(0, 0, 0, 0)","offset":0}],"offsetX":0,"offsetY":0,"gradientUnits":"percentage","gradientTransform":null},"angle":0,"opacity":0.1,"shadow":null,"visible":false,"layerRules":{},"border":{"stroke":"rgba(0, 0, 0, 1)","strokeWidth":0,"strokeDashArray":[0,0]},"globalCompositeOperation":"source-over","selectable":true,"cornerRadius":{"tl":0,"tr":0,"br":0,"bl":0},"scale":1,"groupPath":null,"reflection":null,"zIndex":4,"overrides":{"00d503c2-198a-4040-2ad5-5bbc79f90f6a-412x724":{"zIndex":4}}},"1bceb53e-25c4-4410-a9b6-578964ee0a63":{"type":"image-container","id":"1bceb53e-25c4-4410-a9b6-578964ee0a63","displayText":"Blur Top","dataType":"IMAGE","left":25.89,"top":0,"width":360,"height":60,"angle":0,"opacity":1,"filter":{"brightness":0,"saturation":0,"contrast":0,"invert":false,"blur":0.3},"shadow":{"color":"rgba(0,0,0,0.25)","blur":4,"offsetX":0,"offsetY":4,"affectStroke":false,"nonScaling":false},"visible":true,"globalCompositeOperation":"source-over","selectable":true,"objectPosition":"custom","flipX":false,"flipY":false,"imageOriginX":"center","imageOriginY":"center","border":{"stroke":"rgba(0, 0, 0, 1)","strokeWidth":0,"strokeDashArray":[0,0]},"fill":"transparent","padding":{"top":0,"right":0,"bottom":0,"left":0},"cornerRadius":{"tl":0,"tr":0,"bl":30.030497685185182,"br":30.030497685185182},"objectFit":"crop","imageScale":0.5069899435140655,"imageRotation":0,"imageLeft":-0.25,"imageTop":265.04,"imageWidth":824,"imageHeight":1178,"src":"https://rocketium.com/images/v2/698c18884abb907eb9543a53/canvasPreview/af611575-8224-4e10-3990-eeba29d0f7b7.webp","exportSrc":"https://rocketium.com/images/v2/698c18884abb907eb9543a53/canvasExport/af611575-8224-4e10-3990-eeba29d0f7b7.png","originalSrc":"https://rocketium.com/images/v2/698c18884abb907eb9543a53/original/af611575-8224-4e10-3990-eeba29d0f7b7.png","layerRules":{},"groupPath":null,"reflection":null,"zIndex":5,"overrides":{"00d503c2-198a-4040-2ad5-5bbc79f90f6a-412x724":{"zIndex":5}}},"f79010a3-2137-45ad-bc69-11d8fced81ef":{"id":"f79010a3-2137-45ad-bc69-11d8fced81ef","type":"rounded-rect","dataType":"SHAPE","displayText":"Solid top Copy 1","left":0,"top":0,"width":412,"height":142.44,"fill":{"type":"linear","coords":{"x1":0.5,"y1":0,"x2":0.5,"y2":1},"colorStops":[{"color":"rgba(0, 0, 0, 0)","offset":1},{"color":"rgba(0, 0, 0, 1)","offset":0}],"offsetX":0,"offsetY":0,"gradientUnits":"percentage","gradientTransform":null},"angle":0,"opacity":0.1,"shadow":null,"visible":false,"layerRules":{},"border":{"stroke":"rgba(0, 0, 0, 1)","strokeWidth":0,"strokeDashArray":[0,0]},"globalCompositeOperation":"source-over","selectable":false,"cornerRadius":{"tl":0,"tr":0,"br":0,"bl":0},"scale":1,"groupPath":null,"reflection":null,"zIndex":6,"overrides":{"00d503c2-198a-4040-2ad5-5bbc79f90f6a-412x724":{"zIndex":6}}},"e2f73555-92d4-471a-adf2-309a251735f4":{"id":"e2f73555-92d4-471a-adf2-309a251735f4","type":"rounded-rect","dataType":"SHAPE","displayText":"Solid Top","left":25.89,"top":0,"width":360.22,"height":60,"fill":"rgba(197,197,197,1)","angle":0,"opacity":0.3,"shadow":{"color":"rgba(0,0,0,0.25)","blur":4,"offsetX":0,"offsetY":4,"affectStroke":false,"nonScaling":false},"visible":true,"layerRules":{},"border":{"stroke":"rgba(0, 0, 0, 1)","strokeWidth":0,"strokeDashArray":[0,0]},"globalCompositeOperation":"source-over","selectable":true,"cornerRadius":{"tl":0,"tr":0,"br":30.030497685185182,"bl":30.030497685185182},"scale":1,"groupPath":null,"reflection":null,"zIndex":7,"overrides":{"00d503c2-198a-4040-2ad5-5bbc79f90f6a-412x724":{"zIndex":7}}},"ecceaacb-2ee1-40cc-0f25-1af16a414803":{"type":"image-container","id":"ecceaacb-2ee1-40cc-0f25-1af16a414803","displayText":"Logo 1","dataType":"IMAGE","left":25.76,"top":505.99,"width":161.02,"height":58.99,"angle":0,"opacity":1,"filter":{"brightness":1,"saturation":0,"contrast":0,"invert":false,"blur":0},"shadow":null,"visible":true,"globalCompositeOperation":"source-over","selectable":true,"objectPosition":"center-right","flipX":false,"flipY":false,"imageOriginX":"right","imageOriginY":"center","border":{"stroke":"rgba(0, 0, 0, 1)","strokeWidth":0,"strokeDashArray":[0,0]},"fill":"transparent","padding":{"top":0,"right":0,"bottom":0,"left":0},"cornerRadius":{"tl":0,"tr":0,"bl":0,"br":0},"objectFit":"fit","imageScale":0.04212977498691785,"imageRotation":0,"imageLeft":80.51,"imageTop":0,"imageWidth":3822,"imageHeight":965,"src":"https://rocketium.com/images/v2/62fdb10830765f30f93884a4/canvasPreview/transparentbg/05b67676-8f0e-4d00-3732-582f712e4c60.webp","exportSrc":"https://rocketium.com/images/v2/62fdb10830765f30f93884a4/canvasExport/transparentbg/05b67676-8f0e-4d00-3732-582f712e4c60.png","originalSrc":"https://rocketium.com/images/v2/62fdb10830765f30f93884a4/original/transparentbg/05b67676-8f0e-4d00-3732-582f712e4c60.png","layerRules":{},"groupPath":null,"reflection":null,"zIndex":8,"overrides":{"00d503c2-198a-4040-2ad5-5bbc79f90f6a-412x724":{"zIndex":8}}},"944e9034-527e-4017-83ba-d41082b77107":{"type":"image-container","id":"944e9034-527e-4017-83ba-d41082b77107","displayText":"Logo 2","dataType":"IMAGE","left":225.23,"top":505.99,"width":161.02,"height":58.99,"angle":0,"opacity":1,"filter":{"brightness":1,"saturation":0,"contrast":0,"invert":false,"blur":0},"shadow":null,"visible":true,"globalCompositeOperation":"source-over","selectable":true,"objectPosition":"center-left","flipX":false,"flipY":false,"imageOriginX":"left","imageOriginY":"center","border":{"stroke":"rgba(0, 0, 0, 1)","strokeWidth":0,"strokeDashArray":[0,0]},"fill":"transparent","padding":{"top":0,"right":0,"bottom":0,"left":0},"cornerRadius":{"tl":0,"tr":0,"bl":0,"br":0},"objectFit":"fit","imageScale":0.04212977498691785,"imageRotation":0,"imageLeft":-80.51,"imageTop":0,"imageWidth":3822,"imageHeight":965,"src":"https://rocketium.com/images/v2/62fdb10830765f30f93884a4/canvasPreview/transparentbg/05b67676-8f0e-4d00-3732-582f712e4c60.webp","exportSrc":"https://rocketium.com/images/v2/62fdb10830765f30f93884a4/canvasExport/transparentbg/05b67676-8f0e-4d00-3732-582f712e4c60.png","originalSrc":"https://rocketium.com/images/v2/62fdb10830765f30f93884a4/original/transparentbg/05b67676-8f0e-4d00-3732-582f712e4c60.png","layerRules":{},"groupPath":null,"reflection":null,"zIndex":9,"overrides":{"00d503c2-198a-4040-2ad5-5bbc79f90f6a-412x724":{"zIndex":9}}},"130624f2-70d7-41af-9f9b-ae3f79a07438":{"id":"130624f2-70d7-41af-9f9b-ae3f79a07438","type":"rounded-rect","dataType":"SHAPE","displayText":"Shape 1","left":205.23,"top":506,"width":1,"height":58.99,"fill":"rgba(255, 255, 255, 1)","angle":0,"opacity":1,"shadow":null,"visible":true,"layerRules":{},"border":{"stroke":"rgba(0, 0, 0, 1)","strokeWidth":0,"strokeDashArray":[0,0]},"globalCompositeOperation":"source-over","selectable":true,"cornerRadius":{"tl":0,"tr":0,"br":0,"bl":0},"scale":1,"groupPath":null,"reflection":null,"zIndex":10,"overrides":{"00d503c2-198a-4040-2ad5-5bbc79f90f6a-412x724":{"zIndex":10}}},"8a954e1f-4775-40b1-9b00-b78e811f54ce":{"type":"text-container","id":"8a954e1f-4775-40b1-9b00-b78e811f54ce","dataType":"TEXT","displayText":"Text 1","left":32.5,"top":8,"width":347,"height":44,"angle":0,"opacity":1,"visible":true,"selectable":true,"objectPosition":"center","border":{"stroke":"rgba(0, 0, 0, 1)","strokeWidth":0,"strokeDashArray":[0,0]},"fill":"transparent","padding":{"top":0,"right":0,"bottom":0,"left":0},"cornerRadius":{"tl":0,"tr":0,"bl":0,"br":0},"autoFit":false,"autoFitSizes":[4,590],"textCase":"none","serializedText":"Dresses","fontMetaData":{"fontId":"65fbf0eae299d314b659a38f","fontUrl":"https://rocketium.com/google-fonts/Inter/500.woff2","name":"Inter"},"shadow":null,"globalCompositeOperation":"source-over","textleft":0,"textTop":0,"textHeight":31.23,"textFill":"rgba(255, 255, 255, 1)","fontFamily":"65fbf0eae299d314b659a38f","fontWeight":500,"fontSize":27.64,"text":"Dresses","underline":false,"overline":false,"linethrough":false,"textAlign":"center","fontStyle":"normal","lineHeight":1,"charSpacing":-20,"wordStyle":[],"missingGlyphChars":[],"layerRules":{},"wordSpacing":0,"reflection":null,"groupPath":null,"linethroughOffset":-0.315,"underlineOffset":0.1,"zIndex":11,"overrides":{"00d503c2-198a-4040-2ad5-5bbc79f90f6a-412x724":{"zIndex":11}}},"b0760497-f0f9-4c5b-1d1e-56496806aa00":{"type":"image-container","id":"b0760497-f0f9-4c5b-1d1e-56496806aa00","displayText":"Image 1","dataType":"IMAGE","left":0,"top":0,"width":412,"height":724,"angle":0,"opacity":0.7,"filter":{"brightness":0,"saturation":0,"contrast":0,"invert":false,"blur":0},"shadow":null,"visible":false,"globalCompositeOperation":"source-over","selectable":false,"objectPosition":"center","flipX":false,"flipY":false,"imageOriginX":"center","imageOriginY":"center","border":{"stroke":"rgba(0, 0, 0, 1)","strokeWidth":0,"strokeDashArray":[0,0]},"fill":"transparent","padding":{"top":0,"right":0,"bottom":0,"left":0},"cornerRadius":{"tl":0,"tr":0,"bl":0,"br":0},"objectFit":"fit","imageScale":0.558641975308642,"imageRotation":0,"imageLeft":0,"imageTop":0,"imageWidth":732,"imageHeight":1296,"src":"https://rocketium.com/images/v2/6465b5ef12dd262b452cdd18/canvasPreview/72db1876-14bc-44e0-9965-e3fa0735a639.webp","exportSrc":"https://rocketium.com/images/v2/6465b5ef12dd262b452cdd18/canvasExport/72db1876-14bc-44e0-9965-e3fa0735a639.png","originalSrc":"https://rocketium.com/images/v2/6465b5ef12dd262b452cdd18/original/72db1876-14bc-44e0-9965-e3fa0735a639.png","layerRules":{},"groupPath":null,"reflection":null,"zIndex":12,"overrides":{"00d503c2-198a-4040-2ad5-5bbc79f90f6a-412x724":{"zIndex":12}}},"339763a8-5d4d-4a33-a419-7c5dc162b4eb":{"type":"text-container","id":"339763a8-5d4d-4a33-a419-7c5dc162b4eb","dataType":"TEXT","displayText":"Text 2","left":5.33,"top":604.01,"width":401.34,"height":54,"angle":0,"opacity":1,"visible":true,"selectable":true,"objectPosition":"center","border":{"stroke":"rgba(0, 0, 0, 1)","strokeWidth":0,"strokeDashArray":[0,0]},"fill":"transparent","padding":{"top":0,"right":0,"bottom":0,"left":0},"cornerRadius":{"tl":0,"tr":0,"bl":0,"br":0},"autoFit":false,"autoFitSizes":[4,590],"textCase":"none","serializedText":"Up to 50% off","fontMetaData":{"fontId":"65fbf0eae299d314b659a38f","fontUrl":"https://rocketium.com/google-fonts/Inter/600.woff2","name":"Inter"},"shadow":null,"globalCompositeOperation":"source-over","textleft":0,"textTop":0,"textHeight":46.33,"textFill":"rgba(20,38,54,1)","fontFamily":"65fbf0eae299d314b659a38f","fontWeight":600,"fontSize":41,"text":"Up to 50% off","underline":false,"overline":false,"linethrough":false,"textAlign":"center","fontStyle":"normal","lineHeight":1,"charSpacing":0,"wordStyle":[],"missingGlyphChars":[],"layerRules":{},"wordSpacing":0,"reflection":null,"groupPath":null,"linethroughOffset":-0.315,"underlineOffset":0.1,"zIndex":13,"overrides":{"00d503c2-198a-4040-2ad5-5bbc79f90f6a-412x724":{"zIndex":13}}},"e8627ff2-7b55-4907-9149-d84fb6bf9669":{"type":"text-container","id":"e8627ff2-7b55-4907-9149-d84fb6bf9669","dataType":"TEXT","displayText":"Text 2 Copy 1","left":4.76,"top":661,"width":402.48,"height":37,"angle":0,"opacity":1,"visible":true,"selectable":true,"objectPosition":"center","border":{"stroke":"rgba(0, 0, 0, 1)","strokeWidth":0,"strokeDashArray":[0,0]},"fill":"transparent","padding":{"top":0,"right":0,"bottom":0,"left":0},"cornerRadius":{"tl":0,"tr":0,"bl":0,"br":0},"autoFit":false,"autoFitSizes":[4,590],"textCase":"none","serializedText":"+ Extra 10% off","fontMetaData":{"fontId":"65fbf0eae299d314b659a38f","fontUrl":"https://rocketium.com/google-fonts/Inter/600.woff2","name":"Inter"},"shadow":null,"globalCompositeOperation":"source-over","textleft":0,"textTop":0,"textHeight":37.52,"textFill":"rgba(20,38,54,1)","fontFamily":"65fbf0eae299d314b659a38f","fontWeight":600,"fontSize":33.2,"text":"+ Extra 10% off","underline":false,"overline":false,"linethrough":false,"textAlign":"center","fontStyle":"normal","lineHeight":1,"charSpacing":0,"wordStyle":[],"missingGlyphChars":[],"layerRules":{},"wordSpacing":0,"reflection":null,"groupPath":null,"linethroughOffset":-0.315,"underlineOffset":0.1,"zIndex":14,"overrides":{"00d503c2-198a-4040-2ad5-5bbc79f90f6a-412x724":{"zIndex":14}}}}}},"capsuleErrors":[],"cards":[{"id":"1776505787052","tags":[],"type":"text","groups":[]}],"collaborators":[],"createdAt":"2026-04-20T06:12:05.864Z","creationStatus":{"status":"generated","generationTime":8.137,"numberOfCreatives":1,"progress":100,"time":"2026-03-23T05:42:51.344Z","_id":"69c0d2dbecffed26f9f593e2"},"creativesOrder":["00d503c2-198a-4040-2ad5-5bbc79f90f6a-412x724"],"customDimensions":{"width":412,"height":724,"_id":"69e5c3b54c17a1373136900c"},"exportSettings":{"_id":"68f0aad8070f21e34ac8495a"},"generatedBy":"6465b5ef12dd262b452cdd18","generatedCount":1,"image":"//rocketium.com/assets/images/default/Green-Bubbles.jpg","imageUrl":"https://rocketium.com/images/export/68f0ab010d0b92d9e3b3e805/image-1760602882077.png","isDeleted":false,"lastModified":"Vanishree K - Rocketium","lastModifiedId":"6465b5ef12dd262b452cdd18","listId":"623a177218b0b745935d7a4e","metadata":{"_id":"69c0d2d3ecffed26f9f593d9","isSaved":false,"name":"Variant 1","assetGroup":"asset-group-69e5c38d6826b2da8c1d57a7","email":"sampada.haralkar@nykaa.com","platform":"campaign"},"name":"Variant 1","orientation":"landscape","outputFormat":"image","platform":"web","publishId":"template_6995779c3ff3f60a3c9e9102_1774244561596","savedCustomDimensions":{"00d503c2-198a-4040-2ad5-5bbc79f90f6a-412x724":{"active":true,"name":"412x724","creativeUrl":"https://rocketium.com/images/export/6995779c3ff3f60a3c9e9102/412x724-00d503c2-198a-4040-2ad5-5bbc79f90f6a-412x724-1774244570561.png","width":412,"height":724,"thumbnail":"https://rocketium.com/images/thumbnail/6995779c3ff3f60a3c9e9102/412x724-00d503c2-198a-4040-2ad5-5bbc79f90f6a-412x724-1774244563196.webp","creativeHtmlUrl":null}},"shortId":"2c3f0b4d-cbbf-4221-27dc-7ec93621a4b0","sourceCapsuleId":null,"tags":[],"teamId":"623a177218b0b745935d7a49","templateId":"6995779d3ff3f60a3c9e910f","themeId":"6995779dd76f5216fd9f9b2e","timestamp":"2026-04-20T06:12:04.683Z","title":"Variant 1","updatedAt":"2026-04-20T06:12:05.864Z","videoBackground":"","videoGenerationId":"6995779da030f3ddee517f2d","videoIndex":-1771403164898,"videoLength":0,"visibility":"PUBLIC","watermark":false,"withCanvas":true}]}